{"type": "Feature", "id": 12510851, "properties": {"woe:id": 12510851, "woe:parent_id": 972119, "woe:name": "Kleine Brogel Airport", "woe:placetype": 14, "woe:placetype_name": "Airport", "woe:lang": "ENG", "iso:country": "BE", "meta:provider": ["geoplanet:7.3.1", "geoplanet:7.3.2", "geoplanet:7.4.0", "geoplanet:7.4.1", "geoplanet:7.5.1", "geoplanet:7.5.2", "geoplanet:7.6.0", "geoplanet:7.8.1", "geoplanet:7.9.0", "geoplanet:7.10.0", "geoplanet:8.0.0", "woeplanet:8.0.0"], "meta:indexed": "2020-08-20T20:19:53.325469", "meta:updated": "2020-08-22T01:57:40.622180", "woe:hierarchy": {"continent": 24865675, "country": 23424757, "town": 0, "planet": 1, "county": 12591765, "suburb": 0, "state": 7153301, "region": 0, "localadmin": 12602293}, "woe:timezone_id": 28350891, "woe:hash": "u15gh7pvjgeu", "woe:centroid": [5.4711, 51.169701], "geom:latitude": 51.169701, "geom:longitude": 5.4711, "geom:hash": "u15gh7pvjgeu", "woe:latitude": 51.169701, "geom:centroid": [5.4711, 51.169701], "woe:longitude": 5.4711, "woe:repo": "woeplanet-airport-be"}, "geometry": {"coordinates": [5.4711, 51.169701], "type": "Point"}}