{"type": "Feature", "id": 56051714, "geometry": {"type": "Point", "coordinates": [5.91028, 50.47757]}, "properties": {"woe:id": 56051714, "woe:parent_id": 977072, "woe:name": "Spa A\u00e9rodr\u00f4me", "woe:placetype": 14, "woe:placetype_name": "Airport", "woe:lang": "FRE", "iso:country": "BE", "meta:provider": ["geoplanet:7.3.1", "geoplanet:7.3.2", "geoplanet:7.4.0", "geoplanet:7.4.1", "geoplanet:7.5.1", "geoplanet:7.5.2", "geoplanet:7.6.0", "geoplanet:7.8.1", "geoplanet:7.9.0", "geoplanet:7.10.0", "geoplanet:8.0.0", "woeplanet:8.0.0"], "meta:indexed": "2020-08-20T20:19:53.337949", "meta:updated": "2020-10-14T11:43:42.107837", "woe:alias_FRE_S": ["Spa Aerodrome"], "woe:alias_FRE_V": ["La Sauveni\u00e8re", "La Sauveniere"], "woe:hierarchy": {"continent": 24865675, "country": 23424757, "town": 0, "planet": 1, "county": 12591792, "suburb": 0, "state": 7153300, "region": 0, "localadmin": 12602772}, "woe:timezone_id": 28350891, "woe:hash": "u0upnmptpt01", "woe:centroid": [5.91028, 50.47757], "geom:latitude": 50.47757, "geom:longitude": 5.91028, "geom:hash": "u0upnmptpt01", "woe:latitude": 50.47757, "geom:centroid": [5.91028, 50.47757], "woe:longitude": 5.91028, "woe:repo": "woeplanet-airport-be", "geom:area": 0.0, "woe:scale": 19}}