{"type": "Feature", "id": 12510853, "geometry": {"type": "Point", "coordinates": [3.20578, 50.817039]}, "properties": {"woe:id": 12510853, "woe:parent_id": 967359, "woe:name": "Kortrijk Wevelgem Airport", "woe:placetype": 14, "woe:placetype_name": "Airport", "woe:lang": "ENG", "iso:country": "BE", "meta:provider": ["geoplanet:7.3.1", "geoplanet:7.3.2", "geoplanet:7.4.0", "geoplanet:7.4.1", "geoplanet:7.5.1", "geoplanet:7.5.2", "geoplanet:7.6.0", "geoplanet:7.8.1", "geoplanet:7.9.0", "geoplanet:7.10.0", "geoplanet:8.0.0", "woeplanet:8.0.0"], "meta:indexed": "2020-08-20T20:19:53.333119", "woe:alias_ENG_V": ["KJK", "KJK Airport", "Kortrijk Wevelgem"], "woe:alias_DUT_Q": ["Westvlaamse Interkommunale Vliegveld Wevelgem-Bissegem"], "meta:updated": "2020-10-14T11:43:42.112478", "woe:hierarchy": {"continent": 24865675, "country": 23424757, "town": 0, "planet": 1, "county": 12591766, "suburb": 0, "state": 7153305, "region": 0, "localadmin": 12602664}, "woe:timezone_id": 28350891, "woe:hash": "u1430fyqsndv", "woe:centroid": [3.20578, 50.817039], "geom:latitude": 50.817039, "geom:longitude": 3.20578, "geom:hash": "u1430fyqsndv", "woe:latitude": 50.817039, "geom:centroid": [3.20578, 50.817039], "woe:longitude": 3.20578, "woe:repo": "woeplanet-airport-be", "geom:area": 0.0, "woe:scale": 19}}